slack/__init__.py
slack/attachment.py
slack/base.py
slack/block.py
slack/channel.py
slack/client.py
slack/errors.py
slack/httpclient.py
slack/member.py
slack/message.py
slack/route.py
slack/state.py
slack/team.py
slack/utils.py
slack/ws.py
slack/commands/__init__.py
slack/commands/bot.py
slack/commands/command.py
slack/commands/context.py
slack/types/__init__.py
slack/types/block.py
slack/types/channel.py
slack/types/file.py
slack/types/member.py
slack/types/message.py
slack/types/team.py
slack/types/usergroup.py
slack/view/__init__.py
slack/view/button.py
slack/view/image.py
slack/view/input_text.py
slack/view/modal.py
slack/view/select.py
slack/view/view.py
wsslack.py-1.4.4.dist-info/LICENSE
wsslack.py-1.4.4.dist-info/METADATA
wsslack.py-1.4.4.dist-info/WHEEL
wsslack.py-1.4.4.dist-info/top_level.txt
wsslack.py-1.4.4.dist-info/RECORD
