Metadata-Version: 2.1
Name: wsslack.py
Version: 1.4.4
Summary: An APIwrapper for slack with python.
Home-page: https://github.com/peco2282/slack.py
Author: peco2282
Author-email: pecop2282@gmail.com
License: MIT
Platform: UNKNOWN
License-File: LICENSE
Requires-Dist: aiohttp (<3.9.0,>=3.6.0)
Requires-Dist: typing-extensions (<5,>=4) ; python_version < "3.11"
